[
    {
        "Title": "Tesla to Sell $2 Billion in Shares to Bolster Model 3 Output",
        "Text": [
            "tesla",
            "motors",
            "said",
            "wednesday",
            "would",
            "offer",
            "billion",
            "stock",
            "mainly",
            "help",
            "ramp",
            "production",
            "new",
            "model",
            "electric",
            "car",
            "next",
            "two",
            "years",
            "company",
            "unveiled",
            "model",
            "first",
            "mass",
            "market",
            "car",
            "march",
            "flooded",
            "orders",
            "even",
            "though",
            "compact",
            "sedan",
            "available",
            "year",
            "far",
            "tesla",
            "accepted",
            "deposits",
            "hopeful",
            "buyers",
            "tesla"
        ],
        "Publication": "New York Times",
        "Date": "",
        "Authors": ""
    },
    {
        "Title": "Tesla Says It Will Sharply Ramp Up Production of Model 3",
        "Text": [
            "detroit",
            "tesla",
            "motors",
            "said",
            "wednesday",
            "confident",
            "could",
            "accelerate",
            "production",
            "meet",
            "high",
            "demand",
            "forthcoming",
            "model",
            "electric",
            "vehicle",
            "despite",
            "departure",
            "two",
            "top",
            "manufacturing",
            "executives",
            "carmaker",
            "chief",
            "executive",
            "elon",
            "musk",
            "said",
            "tesla",
            "expected",
            "produce",
            "total",
            "vehicles",
            "two",
            "years",
            "sooner",
            "previously",
            "announced",
            "goal",
            "represents",
            "huge",
            "leap",
            "tesla",
            "production",
            "vehicles",
            "first"
        ],
        "Publication": "New York Times",
        "Date": "",
        "Authors": ""
    },
    {
        "Title": "Tesla\u2019s Model 3 Already Has 325,000 Preorders",
        "Text": [
            "detroit",
            "orders",
            "keep",
            "rolling",
            "forthcoming",
            "model",
            "tesla",
            "motors",
            "said",
            "thursday",
            "received",
            "deposits",
            "newest",
            "electric",
            "cars",
            "extraordinary",
            "response",
            "vehicle",
            "even",
            "built",
            "late",
            "next",
            "year",
            "underscored",
            "demand",
            "among",
            "consumers",
            "mass",
            "market",
            "electric",
            "car",
            "carries",
            "tesla",
            "luxury",
            "brand",
            "cachet",
            "tesla",
            "said",
            "blog",
            "post",
            "number",
            "reservations",
            "corresponded"
        ],
        "Publication": "New York Times",
        "Date": "",
        "Authors": ""
    },
    {
        "Title": "Tesla Model 3 Orders Surge Even Before Its Unveiling",
        "Text": [
            "tesla",
            "motors",
            "says",
            "new",
            "model",
            "meant",
            "bring",
            "company",
            "electric",
            "vehicle",
            "technology",
            "masses",
            "orders",
            "car",
            "even",
            "introduced",
            "well",
            "way",
            "crowd",
            "tesla",
            "fans",
            "cheered",
            "model",
            "sleek",
            "five",
            "seater",
            "unveiled",
            "thursday",
            "evening",
            "company",
            "design",
            "studio",
            "hawthorne",
            "calif",
            "interested",
            "customers",
            "lined",
            "tesla",
            "dealerships",
            "around"
        ],
        "Publication": "New York Times",
        "Date": "",
        "Authors": ""
    },
    {
        "Title": "Tesla\u2019s New Model 3 Jump-Starts Demand for Electric Cars",
        "Text": [
            "detroit",
            "despite",
            "steady",
            "stream",
            "new",
            "models",
            "number",
            "automakers",
            "sales",
            "year",
            "electric",
            "hybrid",
            "vehicles",
            "failed",
            "keep",
            "pace",
            "growth",
            "overall",
            "american",
            "market",
            "market",
            "electrified",
            "cars",
            "slumbering",
            "tesla",
            "motors",
            "woke",
            "jolt",
            "thursday",
            "unveiling",
            "coming",
            "model",
            "lineup",
            "affordable",
            "zero",
            "emission",
            "vehicles",
            "given",
            "electric",
            "hybrid",
            "vehicles",
            "account",
            "percent",
            "last",
            "year",
            "record",
            "setting",
            "sales",
            "united",
            "states",
            "extraordinary",
            "reaction"
        ],
        "Publication": "New York Times",
        "Date": "",
        "Authors": ""
    },
    {
        "Title": "From Tesla, a New Car Smell That Vegans Can Get Behind",
        "Text": [
            "eco",
            "conscious",
            "car",
            "buyer",
            "tesla",
            "luxury",
            "electric",
            "vehicles",
            "neck",
            "snapping",
            "acceleration",
            "proof",
            "performance",
            "sacrificed",
            "altar",
            "saving",
            "environment",
            "discerning",
            "consumers",
            "nagging",
            "problem",
            "leather",
            "seats",
            "steering",
            "wheel",
            "requires",
            "slaughtering",
            "animals",
            "cloth",
            "substitute",
            "quite",
            "measure",
            "vehicle",
            "cost",
            "response",
            "comes",
            "tesla",
            "even",
            "luxury",
            "minded",
            "vegan"
        ],
        "Publication": "New York Times",
        "Date": "",
        "Authors": ""
    },
    {
        "Title": "Tesla Recalls Model X S.U.V.s",
        "Text": [
            "tesla",
            "motors",
            "said",
            "monday",
            "recalling",
            "model",
            "x",
            "sport",
            "utility",
            "vehicles",
            "testing",
            "revealed",
            "backs",
            "electric",
            "car",
            "third",
            "row",
            "seats",
            "could",
            "give",
            "way",
            "crash",
            "voluntary",
            "action",
            "affects",
            "model",
            "xs",
            "built",
            "march",
            "tesla",
            "said",
            "discovered",
            "problem",
            "performing",
            "tests",
            "required",
            "european",
            "safety",
            "regulators",
            "company",
            "said",
            "reports",
            "accidents",
            "related",
            "problem",
            "added",
            "vehicle",
            "passed",
            "american",
            "crash",
            "tests",
            "recall",
            "comes",
            "face"
        ],
        "Publication": "New York Times",
        "Date": "",
        "Authors": ""
    },
    {
        "Title": "",
        "Text": [],
        "Publication": "New York Times",
        "Date": "",
        "Authors": ""
    },
    {
        "Title": "Consumer Reports Stops Recommending the Tesla ",
        "Text": [
            "consumer",
            "reports",
            "dropped",
            "recommendation",
            "tesla",
            "model",
            "owners",
            "electric",
            "luxury",
            "sedan",
            "complained",
            "series",
            "problems",
            "including",
            "squeaking",
            "noises",
            "motors",
            "needed",
            "changed",
            "issues",
            "car",
            "automatic",
            "door",
            "handles",
            "change",
            "came",
            "consumer",
            "group",
            "reviewed",
            "reports",
            "model",
            "owners",
            "part",
            "annual",
            "survey",
            "found",
            "chronicled",
            "array",
            "detailed",
            "complicated",
            "maladies",
            "concluded",
            "model",
            "many",
            "problems",
            "recommend",
            "surprise",
            "change"
        ],
        "Publication": "New York Times",
        "Date": "",
        "Authors": ""
    },
    {
        "Title": "Tesla Adds High-Speed Autonomous Driving to Its Bag of Tricks",
        "Text": [
            "washington",
            "every",
            "day",
            "get",
            "open",
            "door",
            "step",
            "future",
            "pull",
            "handle",
            "newly",
            "updated",
            "tesla",
            "model",
            "week",
            "slide",
            "driver",
            "seat",
            "catch",
            "glimpse",
            "auto",
            "industry",
            "plans",
            "soon",
            "let",
            "cars",
            "drive",
            "us",
            "rather",
            "way",
            "around",
            "updated",
            "tesla",
            "already",
            "high",
            "tech",
            "electric",
            "car",
            "starts",
            "equipped",
            "company",
            "calls",
            "autopilot",
            "semiautonomous"
        ],
        "Publication": "New York Times",
        "Date": "",
        "Authors": ""
    },
    {
        "Title": "Tesla Delivers Model X, Its First Sport Utility Vehicle",
        "Text": [
            "tesla",
            "motors",
            "delivering",
            "first",
            "sport",
            "utility",
            "vehicles",
            "adding",
            "second",
            "model",
            "lineup",
            "seeks",
            "attract",
            "buyers",
            "electric",
            "vehicles",
            "late",
            "evening",
            "event",
            "tuesday",
            "factory",
            "fremont",
            "calif",
            "served",
            "highlight",
            "importance",
            "new",
            "vehicle",
            "model",
            "x",
            "tesla",
            "growth",
            "future",
            "profitability",
            "show",
            "vintage",
            "tesla",
            "exuberant",
            "mix",
            "technology",
            "salesmanship",
            "hype",
            "two",
            "years",
            "delays",
            "money",
            "losing",
            "electric",
            "car",
            "company",
            "seemed",
            "eager",
            "show",
            "moving",
            "ahead"
        ],
        "Publication": "New York Times",
        "Date": "",
        "Authors": ""
    }
]